LICENSE
README.rst
setup.py
aliyunsdkcms/__init__.py
aliyunsdkcms.egg-info/PKG-INFO
aliyunsdkcms.egg-info/SOURCES.txt
aliyunsdkcms.egg-info/dependency_links.txt
aliyunsdkcms.egg-info/requires.txt
aliyunsdkcms.egg-info/top_level.txt
aliyunsdkcms/request/__init__.py
aliyunsdkcms/request/v20190101/AddTagsRequest.py
aliyunsdkcms/request/v20190101/ApplyMetricRuleTemplateRequest.py
aliyunsdkcms/request/v20190101/BatchCreateIntantSiteMonitorRequest.py
aliyunsdkcms/request/v20190101/CreateCmsCallNumOrderRequest.py
aliyunsdkcms/request/v20190101/CreateCmsOrderRequest.py
aliyunsdkcms/request/v20190101/CreateCmsSmspackageOrderRequest.py
aliyunsdkcms/request/v20190101/CreateDynamicTagGroupRequest.py
aliyunsdkcms/request/v20190101/CreateGroupMetricRulesRequest.py
aliyunsdkcms/request/v20190101/CreateGroupMonitoringAgentProcessRequest.py
aliyunsdkcms/request/v20190101/CreateHostAvailabilityRequest.py
aliyunsdkcms/request/v20190101/CreateHybridMonitorNamespaceRequest.py
aliyunsdkcms/request/v20190101/CreateHybridMonitorSLSGroupRequest.py
aliyunsdkcms/request/v20190101/CreateHybridMonitorTaskRequest.py
aliyunsdkcms/request/v20190101/CreateInstantSiteMonitorRequest.py
aliyunsdkcms/request/v20190101/CreateMetricRuleResourcesRequest.py
aliyunsdkcms/request/v20190101/CreateMetricRuleTemplateRequest.py
aliyunsdkcms/request/v20190101/CreateMonitorAgentProcessRequest.py
aliyunsdkcms/request/v20190101/CreateMonitorGroupByResourceGroupIdRequest.py
aliyunsdkcms/request/v20190101/CreateMonitorGroupInstancesRequest.py
aliyunsdkcms/request/v20190101/CreateMonitorGroupNotifyPolicyRequest.py
aliyunsdkcms/request/v20190101/CreateMonitorGroupRequest.py
aliyunsdkcms/request/v20190101/CreateMonitoringAgentProcessRequest.py
aliyunsdkcms/request/v20190101/CreateSiteMonitorRequest.py
aliyunsdkcms/request/v20190101/DeleteContactGroupRequest.py
aliyunsdkcms/request/v20190101/DeleteContactRequest.py
aliyunsdkcms/request/v20190101/DeleteCustomMetricRequest.py
aliyunsdkcms/request/v20190101/DeleteDynamicTagGroupRequest.py
aliyunsdkcms/request/v20190101/DeleteEventRuleTargetsRequest.py
aliyunsdkcms/request/v20190101/DeleteEventRulesRequest.py
